gestalt/__init__.py
gestalt/compression.py
gestalt/runner.py
gestalt/serialization.py
gestalt/timer.py
gestalt/amq/__init__.py
gestalt/amq/consumer.py
gestalt/amq/producer.py
gestalt/amq/requester.py
gestalt/amq/responder.py
gestalt/amq/utils.py
gestalt/comms/__init__.py
gestalt/comms/amq/__init__.py
gestalt/comms/amq/consumer.py
gestalt/comms/amq/producer.py
gestalt/comms/amq/utils.py
gestalt/comms/stream/__init__.py
gestalt/comms/stream/endpoint.py
gestalt/comms/stream/mti.py
gestalt/comms/stream/netstring.py
gestalt/comms/stream/protocols/__init__.py
gestalt/comms/stream/protocols/base.py
gestalt/comms/stream/protocols/mti.py
gestalt/comms/stream/protocols/netstring.py
gestalt/datagram/__init__.py
gestalt/datagram/endpoint.py
gestalt/datagram/mti.py
gestalt/datagram/netstring.py
gestalt/datagram/protocols/__init__.py
gestalt/datagram/protocols/base.py
gestalt/datagram/protocols/mti.py
gestalt/datagram/protocols/netstring.py
gestalt/stream/__init__.py
gestalt/stream/endpoint.py
gestalt/stream/mti.py
gestalt/stream/netstring.py
gestalt/stream/protocols/__init__.py
gestalt/stream/protocols/base.py
gestalt/stream/protocols/mti.py
gestalt/stream/protocols/netstring.py
gestalt-20.1.1.dist-info/METADATA
gestalt-20.1.1.dist-info/WHEEL
gestalt-20.1.1.dist-info/top_level.txt
gestalt-20.1.1.dist-info/RECORD
