Metadata-Version: 2.1
Name: gestalt
Version: 20.1.1
Summary: gestalt is a Python application framework for building distributed systems
Home-page: https://github.com/claws/gestalt
Author: Chris Laws
License: MIT license
Keywords: gestalt,framework,communications
Platform: UNKNOWN
Classifier: Development Status :: 4 - Beta
Classifier: Intended Audience :: Developers
Classifier: Programming Language :: Python :: 3.6
Classifier: Programming Language :: Python :: 3.7
Classifier: Programming Language :: Python :: 3.8
Classifier: Programming Language :: Python :: Implementation :: CPython
Requires-Python: >=3.6
Requires-Dist: yarl
Provides-Extra: amq
Requires-Dist: aio-pika ; extra == 'amq'
Provides-Extra: avro
Requires-Dist: avro-python3 ; extra == 'avro'
Provides-Extra: brotli
Requires-Dist: brotli ; extra == 'brotli'
Provides-Extra: develop
Requires-Dist: asynctest ; extra == 'develop'
Requires-Dist: black ; extra == 'develop'
Requires-Dist: coverage ; extra == 'develop'
Requires-Dist: mypy ; extra == 'develop'
Requires-Dist: m2r ; extra == 'develop'
Requires-Dist: pylint ; extra == 'develop'
Requires-Dist: sphinx ; extra == 'develop'
Requires-Dist: twine ; extra == 'develop'
Requires-Dist: wheel ; extra == 'develop'
Requires-Dist: grpcio-tools ; extra == 'develop'
Provides-Extra: msgpack
Requires-Dist: msgpack-python ; extra == 'msgpack'
Provides-Extra: protobuf
Requires-Dist: protobuf ; extra == 'protobuf'
Provides-Extra: snappy
Requires-Dist: python-snappy ; extra == 'snappy'
Provides-Extra: yaml
Requires-Dist: PyYAML ; extra == 'yaml'
